ptol/__init__.py
ptol/download_pdfs.py
ptol/main.py
ptol/pdf_to_text.py
ptol/query_syntax.py
ptol/remove_duplicates.py
ptol-0.1.2.dist-info/METADATA
ptol-0.1.2.dist-info/WHEEL
ptol-0.1.2.dist-info/entry_points.txt
ptol-0.1.2.dist-info/top_level.txt
ptol-0.1.2.dist-info/RECORD
