Metadata-Version: 2.1
Name: ptol
Version: 0.1.2
Summary: A Pipeline for Obtaining Relevant Literature Based on Given Keywords
Home-page: https://github.com/ChenHuilong1223/Pipeline_to_literature
Author: Huilong Chen
Author-email: chenhuilong131@163.com
License: MIT License
Platform: UNKNOWN
Classifier: Intended Audience :: Science/Research
Classifier: Programming Language :: Python :: 3
Classifier: License :: OSI Approved :: MIT License
Classifier: Operating System :: OS Independent
Requires-Python: >=3.8
Requires-Dist: pandas
Requires-Dist: selenium
Requires-Dist: nltk
Requires-Dist: inflect
Requires-Dist: PyPDF2
Requires-Dist: pdfplumber
Requires-Dist: PyMuPDF
Requires-Dist: pdfminer.six
